Metadata-Version: 2.1
Name: nflwin
Version: 1.0.1
Summary: A Python implementation of NFL Win Probability (WP)
Home-page: https://github.com/AndrewRook/NFLWin
Author: Andrew Schechtman-Rook
Author-email: footballastronomer@gmail.com
Maintainer: Andrew Schechtman-Rook
Maintainer-email: footballastronomer@gmail.com
License: MIT
Keywords: NFL,WP,Win Probability
Platform: UNKNOWN
Classifier: Development Status :: 4 - Beta
Classifier: Natural Language :: English
Classifier: License :: OSI Approved :: MIT License
Classifier: Operating System :: OS Independent
Classifier: Programming Language :: Python
Classifier: Programming Language :: Python :: 2
Classifier: Programming Language :: Python :: 2.7
Provides-Extra: plotting
Provides-Extra: nfldb
Provides-Extra: dev
